mopidris/__init__.py
mopidris/__main__.py
mopidris/mopidris.py
mopidris/interfaces/__init__.py
mopidris/interfaces/base.py
mopidris/interfaces/player.py
mopidris/interfaces/playlists.py
mopidris/interfaces/root.py
mopidris/interfaces/tracklist.py
mopidris-0.9.1.dist-info/LICENSE
mopidris-0.9.1.dist-info/METADATA
mopidris-0.9.1.dist-info/WHEEL
mopidris-0.9.1.dist-info/top_level.txt
mopidris-0.9.1.dist-info/RECORD
