Metadata-Version: 2.1
Name: mopidris
Version: 0.9.1
Summary: MPRIS2 D-Bus for a (remote) Mopidy instance
Home-page: https://codeberg.org/sph/mopidris
Author: Stephan Helma
Author-email: s.p.helma@gmx.net
License: GNU General Public License, Version 3
Project-URL: Bug Tracker, https://gitlab.com/sphh/mopidris/-/issues
Platform: UNKNOWN
Classifier: Development Status :: 5 - Production/Stable
Classifier: Environment :: No Input/Output (Daemon)
Classifier: Framework :: AsyncIO
Classifier: Intended Audience :: End Users/Desktop
Classifier: License :: OSI Approved :: GNU General Public License v3 or later (GPLv3+)
Classifier: Operating System :: OS Independent
Classifier: Programming Language :: Python :: 3
Classifier: Programming Language :: Python :: 3.8
Classifier: Programming Language :: Python :: 3.9
Classifier: Topic :: Multimedia :: Sound/Audio :: Players
Requires-Python: >=3.8
License-File: LICENSE
Requires-Dist: dbus-next (>=0.2.3)
Requires-Dist: mopidy-asyncio-client (>=3.0.1)
Requires-Dist: setuptools
Provides-Extra: dev
Requires-Dist: twine ; extra == 'dev'
Requires-Dist: wheel ; extra == 'dev'
Provides-Extra: release
Requires-Dist: twine ; extra == 'release'
Requires-Dist: wheel ; extra == 'release'
